[{"frames": [{"s": 21, "d": 4}, {"s": 22, "d": 4}, {"s": 23, "d": 4}, {"s": 24, "d": 4}, {"s": 25, "d": 4}, {"s": 26, "d": 4}, {"s": 27, "d": 4}, {"s": 28, "d": 4}, {"s": 29, "d": 4}, {"s": 30, "d": 4}, {"s": 31, "d": 4}, {"s": 32, "d": 4}, {"s": 33, "d": 4}, {"s": 34, "d": 4}, {"s": 35, "d": 4}, {"s": 36, "d": 4}, {"s": 37, "d": 4}]}, {"frames": [{"s": 21, "d": 4}, {"s": 22, "d": 4}, {"s": 23, "d": 4}, {"s": 24, "d": 4}, {"s": 25, "d": 4}, {"s": 26, "d": 4}, {"s": 27, "d": 4}, {"s": 28, "d": 4}, {"s": 29, "d": 4}, {"s": 30, "d": 4}, {"s": 31, "d": 4}, {"s": 32, "d": 4}, {"s": 33, "d": 4}, {"s": 34, "d": 4}, {"s": 35, "d": 4}, {"s": 36, "d": 4}, {"s": 37, "d": 4}]}, {"frames": [{"s": 39, "d": 3}, {"s": 40, "d": 3}, {"s": 41, "d": 3}, {"s": 42, "d": 3}, {"s": 43, "d": 3}, {"s": 44, "d": 3}, {"s": 45, "d": 3}, {"s": 46, "d": 3}, {"s": 47, "d": 3}, {"s": 48, "d": 3}, {"s": 49, "d": 3}, {"s": 50, "d": 3}, {"s": 51, "d": 3}, {"s": 52, "d": 3}, {"s": 53, "d": 3}, {"s": 54, "d": 3}]}, {"frames": [{"s": 55, "d": 3}, {"s": 56, "d": 3}, {"s": 57, "d": 3}, {"s": 58, "d": 3}, {"s": 59, "d": 3}, {"s": 60, "d": 3}, {"s": 61, "d": 3}, {"s": 62, "d": 3}, {"s": 63, "d": 3}, {"s": 64, "d": 3}, {"s": 65, "d": 3}, {"s": 66, "d": 3}, {"s": 67, "d": 3}, {"s": 68, "d": 3}, {"s": 69, "d": 3}, {"s": 70, "d": 3}]}, {"frames": [{"s": 21, "d": 4}, {"s": 22, "d": 4}, {"s": 23, "d": 4}, {"s": 24, "d": 4}, {"s": 25, "d": 4}, {"s": 26, "d": 4}, {"s": 27, "d": 4}, {"s": 28, "d": 4}, {"s": 29, "d": 4}, {"s": 30, "d": 4}, {"s": 31, "d": 4}, {"s": 32, "d": 4}, {"s": 33, "d": 4}, {"s": 34, "d": 4}, {"s": 35, "d": 4}, {"s": 36, "d": 4}, {"s": 37, "d": 4}]}, {"frames": [{"s": 21, "d": 4}, {"s": 22, "d": 4}, {"s": 23, "d": 4}, {"s": 24, "d": 4}, {"s": 25, "d": 4}, {"s": 26, "d": 4}, {"s": 27, "d": 4}, {"s": 28, "d": 4}, {"s": 29, "d": 4}, {"s": 30, "d": 4}, {"s": 31, "d": 4}, {"s": 32, "d": 4}, {"s": 33, "d": 4}, {"s": 34, "d": 4}, {"s": 35, "d": 4}, {"s": 36, "d": 4}, {"s": 37, "d": 4}]}, {"frames": [{"s": 39, "d": 7}, {"s": 40, "d": 7}]}, {"frames": [{"s": 55, "d": 7}, {"s": 56, "d": 7}]}, {"frames": [{"s": 21, "d": 4}, {"s": 22, "d": 4}, {"s": 23, "d": 4}, {"s": 24, "d": 4}, {"s": 25, "d": 4}, {"s": 26, "d": 4}, {"s": 27, "d": 4}, {"s": 28, "d": 4}, {"s": 29, "d": 4}, {"s": 30, "d": 4}, {"s": 31, "d": 4}, {"s": 32, "d": 4}, {"s": 33, "d": 4}, {"s": 34, "d": 4}, {"s": 35, "d": 4}, {"s": 36, "d": 4}, {"s": 37, "d": 4}]}, {"frames": [{"s": 21, "d": 4}, {"s": 22, "d": 4}, {"s": 23, "d": 4}, {"s": 24, "d": 4}, {"s": 25, "d": 4}, {"s": 26, "d": 4}, {"s": 27, "d": 4}, {"s": 28, "d": 4}, {"s": 29, "d": 4}, {"s": 30, "d": 4}, {"s": 31, "d": 4}, {"s": 32, "d": 4}, {"s": 33, "d": 4}, {"s": 34, "d": 4}, {"s": 35, "d": 4}, {"s": 36, "d": 4}, {"s": 37, "d": 4}]}, {"frames": [{"s": 95, "d": 4}, {"s": 79, "d": 4}, {"s": 80, "d": 4}, {"s": 81, "d": 4}, {"s": 82, "d": 4}, {"s": 83, "d": 4}, {"s": 84, "d": 4}, {"s": 83, "d": 2}, {"s": 82, "d": 2}, {"s": 81, "d": 2}, {"s": 80, "d": 2}, {"s": 85, "d": 2}]}, {"frames": [{"s": 95, "d": 4}, {"s": 86, "d": 4}, {"s": 87, "d": 4}, {"s": 88, "d": 4}, {"s": 89, "d": 4}, {"s": 82, "d": 4}, {"s": 83, "d": 4}, {"s": 84, "d": 4}, {"s": 90, "d": 2}, {"s": 91, "d": 2}, {"s": 92, "d": 2}, {"s": 93, "d": 2}]}, {"frames": [{"s": 95, "d": 4}, {"s": 93, "d": 4}, {"s": 92, "d": 4}, {"s": 91, "d": 4}, {"s": 90, "d": 4}, {"s": 84, "d": 4}, {"s": 83, "d": 4}, {"s": 82, "d": 2}, {"s": 89, "d": 2}, {"s": 88, "d": 2}, {"s": 87, "d": 2}, {"s": 86, "d": 2}]}, {"frames": [{"s": 95, "d": 4}, {"s": 38, "d": 4}, {"s": 96, "d": 4}, {"s": 97, "d": 4}]}, {"frames": [{"s": 95, "d": 4}, {"s": 38, "d": 4}, {"s": 96, "d": 4}, {"s": 97, "d": 4}]}, {"frames": [{"s": 95, "d": 4}, {"s": 38, "d": 4}, {"s": 96, "d": 4}, {"s": 97, "d": 4}]}, {"frames": [{"s": 95, "d": 4}, {"s": 79, "d": 4}, {"s": 85, "d": 4}, {"s": 80, "d": 4}, {"s": 85, "d": 4}, {"s": 80, "d": 4}, {"s": 85, "d": 4}, {"s": 80, "d": 4}, {"s": 81, "d": 4}, {"s": 82, "d": 4}, {"s": 83, "d": 4}, {"s": 84, "d": 4}, {"s": 83, "d": 2}, {"s": 82, "d": 2}, {"s": 81, "d": 2}, {"s": 80, "d": 2}, {"s": 85, "d": 2}]}, {"frames": [{"s": 95, "d": 4}, {"s": 86, "d": 4}, {"s": 87, "d": 4}, {"s": 86, "d": 4}, {"s": 87, "d": 4}, {"s": 86, "d": 4}, {"s": 87, "d": 4}, {"s": 88, "d": 4}, {"s": 89, "d": 4}, {"s": 82, "d": 4}, {"s": 83, "d": 4}, {"s": 84, "d": 4}, {"s": 90, "d": 2}, {"s": 91, "d": 2}, {"s": 92, "d": 2}, {"s": 93, "d": 2}]}, {"frames": [{"s": 95, "d": 4}, {"s": 93, "d": 4}, {"s": 92, "d": 4}, {"s": 93, "d": 4}, {"s": 92, "d": 4}, {"s": 93, "d": 4}, {"s": 92, "d": 4}, {"s": 91, "d": 4}, {"s": 90, "d": 4}, {"s": 84, "d": 4}, {"s": 83, "d": 4}, {"s": 82, "d": 4}, {"s": 89, "d": 2}, {"s": 88, "d": 2}, {"s": 87, "d": 2}, {"s": 86, "d": 2}]}, {"frames": [{"s": 80, "d": 2}, {"s": 85, "d": 2}]}, {"frames": [{"s": 92, "d": 2}, {"s": 93, "d": 2}]}, {"frames": [{"s": 87, "d": 2}, {"s": 86, "d": 2}]}, {"frames": [{"s": 299, "d": 4}, {"s": 300, "d": 4}, {"s": 301, "d": 4}]}, {"frames": [{"s": 72, "d": 4}, {"s": 73, "d": 4}, {"s": 74, "d": 2}, {"s": 75, "d": 2}, {"s": 76, "d": 4}, {"s": 71, "d": 4}, {"s": 72, "d": 2}]}, {"frames": [{"s": 77, "d": 4}, {"s": 78, "d": 4}, {"s": 84, "d": 8}, {"s": 83, "d": 4}, {"s": 82, "d": 4}, {"s": 81, "d": 4}, {"s": 80, "d": 4}, {"s": 95, "d": 4}, {"s": 38, "d": 4}, {"s": 96, "d": 4}, {"s": 97, "d": 4}]}, {"frames": [{"s": 21, "d": 4}, {"s": 22, "d": 4}, {"s": 23, "d": 4}, {"s": 24, "d": 4}, {"s": 25, "d": 4}, {"s": 26, "d": 4}, {"s": 27, "d": 4}, {"s": 28, "d": 4}, {"s": 29, "d": 4}, {"s": 30, "d": 4}, {"s": 31, "d": 4}, {"s": 32, "d": 4}, {"s": 33, "d": 4}, {"s": 34, "d": 4}, {"s": 35, "d": 4}, {"s": 36, "d": 4}, {"s": 37, "d": 4}]}, {"frames": [{"s": 21, "d": 4}, {"s": 22, "d": 4}, {"s": 23, "d": 4}, {"s": 24, "d": 4}, {"s": 25, "d": 4}, {"s": 26, "d": 4}, {"s": 27, "d": 4}, {"s": 28, "d": 4}, {"s": 29, "d": 4}, {"s": 30, "d": 4}, {"s": 31, "d": 4}, {"s": 32, "d": 4}, {"s": 33, "d": 4}, {"s": 34, "d": 4}, {"s": 35, "d": 4}, {"s": 36, "d": 4}, {"s": 37, "d": 4}]}, {"frames": [{"s": 94, "d": 6}, {"s": 95, "d": 6}]}, {"frames": [{"s": 38, "d": 4}]}, {"frames": [{"s": 96, "d": 6}, {"s": 97, "d": 6}]}, {"frames": [{"s": 98, "d": 3}, {"s": 99, "d": 2}, {"s": 100, "d": 2}, {"s": 101, "d": 3}, {"s": 102, "d": 2}]}, {"frames": [{"s": 103, "d": 11}]}, {"frames": [{"s": 104, "d": 2}, {"s": 105, "d": 2}, {"s": 106, "d": 2}]}, {"frames": [{"s": 106, "d": 2}]}, {"frames": [{"s": 104, "d": 6}]}, {"frames": [{"s": 106, "d": 2}]}, {"frames": [{"s": 107, "d": 4}, {"s": 108, "d": 4}, {"s": 109, "d": 4}]}, {"frames": [{"s": 109, "d": 4}]}, {"frames": [{"s": 107, "d": 6}]}, {"frames": [{"s": 109, "d": 4}]}, {"frames": [{"s": 110, "d": 4}, {"s": 111, "d": 4}, {"s": 112, "d": 4}]}, {"frames": [{"s": 112, "d": 4}]}, {"frames": [{"s": 112, "d": 4}]}, {"frames": [{"s": 21, "d": 2}, {"s": 182, "d": 1}, {"s": 181, "d": 3}, {"s": 183, "d": 2}, {"s": 183, "d": 1}, {"s": 196, "d": 6}]}, {"frames": [{"s": 184, "d": 2}, {"s": 185, "d": 2}, {"s": 186, "d": 1}, {"s": 187, "d": 1}, {"s": 188, "d": 1}, {"s": 189, "d": 11}, {"s": 196, "d": 6}]}, {"frames": [{"s": 197, "d": 6}, {"s": 198, "d": 2}, {"s": 199, "d": 2}, {"s": 200, "d": 14}, {"s": 201, "d": 8}, {"s": 95, "d": 2}, {"s": 38, "d": 4}, {"s": 96, "d": 4}, {"s": 97, "d": 2}]}, {"frames": [{"s": 21, "d": 4}, {"s": 182, "d": 1}, {"s": 181, "d": 6}, {"s": 183, "d": 5}, {"s": 196, "d": 4}]}, {"frames": [{"s": 190, "d": 1}, {"s": 191, "d": 4}, {"s": 192, "d": 1}, {"s": 193, "d": 1}, {"s": 194, "d": 1}, {"s": 195, "d": 12}, {"s": 196, "d": 6}]}, {"frames": [{"s": 197, "d": 6}, {"s": 198, "d": 2}, {"s": 199, "d": 2}, {"s": 200, "d": 14}, {"s": 201, "d": 8}, {"s": 95, "d": 2}, {"s": 38, "d": 4}, {"s": 96, "d": 4}, {"s": 97, "d": 2}]}, {"frames": [{"s": 202, "d": 2}, {"s": 203, "d": 1}, {"s": 204, "d": 4}, {"s": 205, "d": 6}]}, {"frames": [{"s": 21, "d": 5}, {"s": 206, "d": 2}, {"s": 207, "d": 3}, {"s": 207, "d": 7}, {"s": 399, "d": 4}, {"s": 96, "d": 4}]}, {"frames": [{"s": 243, "d": 5}, {"s": 244, "d": 1}, {"s": 245, "d": 2}, {"s": 245, "d": 2}, {"s": 245, "d": 8}, {"s": 246, "d": 4}, {"s": 247, "d": 4}, {"s": 248, "d": 6}, {"s": 94, "d": 5}, {"s": 95, "d": 4}]}, {"frames": [{"s": 202, "d": 2}, {"s": 203, "d": 1}, {"s": 204, "d": 4}, {"s": 205, "d": 6}]}, {"frames": [{"s": 208, "d": 1}, {"s": 209, "d": 4}, {"s": 209, "d": 4}, {"s": 210, "d": 6}, {"s": 399, "d": 2}, {"s": 95, "d": 2}, {"s": 38, "d": 2}]}, {"frames": [{"s": 243, "d": 5}, {"s": 244, "d": 1}, {"s": 245, "d": 2}, {"s": 245, "d": 2}, {"s": 245, "d": 8}, {"s": 246, "d": 4}, {"s": 247, "d": 4}, {"s": 248, "d": 6}, {"s": 94, "d": 5}, {"s": 95, "d": 4}]}, {"frames": [{"s": 38, "d": 2}, {"s": 218, "d": 2}, {"s": 219, "d": 6}, {"s": 38, "d": 6}]}, {"frames": [{"s": 220, "d": 1}, {"s": 221, "d": 4}, {"s": 222, "d": 1}, {"s": 223, "d": 2}, {"s": 224, "d": 8}, {"s": 225, "d": 6}, {"s": 226, "d": 2}, {"s": 95, "d": 2}]}, {"frames": [{"s": 95, "d": 2}, {"s": 227, "d": 2}, {"s": 228, "d": 4}, {"s": 229, "d": 4}, {"s": 230, "d": 1}, {"s": 231, "d": 1}, {"s": 232, "d": 2}, {"s": 233, "d": 4}, {"s": 233, "d": 12}]}, {"frames": [{"s": 38, "d": 6}, {"s": 218, "d": 2}, {"s": 219, "d": 6}, {"s": 38, "d": 6}]}, {"frames": [{"s": 220, "d": 1}, {"s": 221, "d": 4}, {"s": 222, "d": 1}, {"s": 223, "d": 2}, {"s": 224, "d": 8}, {"s": 225, "d": 6}, {"s": 226, "d": 2}, {"s": 95, "d": 2}]}, {"frames": [{"s": 375, "d": 6}, {"s": 376, "d": 3}, {"s": 377, "d": 3}, {"s": 376, "d": 3}, {"s": 377, "d": 3}, {"s": 376, "d": 3}, {"s": 377, "d": 3}, {"s": 378, "d": 3}, {"s": 379, "d": 3}, {"s": 149, "d": 3}, {"s": 150, "d": 3}, {"s": 151, "d": 3}, {"s": 95, "d": 2}, {"s": 96, "d": 2}]}, {"frames": [{"s": 38, "d": 1}, {"s": 234, "d": 3}, {"s": 235, "d": 2}, {"s": 236, "d": 4}, {"s": 234, "d": 6}]}, {"frames": [{"s": 237, "d": 4}, {"s": 238, "d": 1}, {"s": 239, "d": 8}, {"s": 240, "d": 6}, {"s": 241, "d": 6}, {"s": 242, "d": 4}]}, {"frames": [{"s": 213, "d": 1}, {"s": 213, "d": 5}, {"s": 214, "d": 2}, {"s": 215, "d": 8}, {"s": 216, "d": 4}, {"s": 217, "d": 4}, {"s": 217, "d": 4}, {"s": 217, "d": 4}, {"s": 38, "d": 4}]}, {"frames": [{"s": 249, "d": 2}, {"s": 250, "d": 1}, {"s": 251, "d": 9}, {"s": 249, "d": 10}]}, {"frames": [{"s": 252, "d": 4}, {"s": 253, "d": 4}, {"s": 255, "d": 6}, {"s": 255, "d": 12}]}, {"frames": [{"s": 261, "d": 4}, {"s": 262, "d": 2}, {"s": 263, "d": 2}, {"s": 264, "d": 2}, {"s": 264, "d": 4}, {"s": 265, "d": 4}, {"s": 266, "d": 4}, {"s": 267, "d": 4}, {"s": 81, "d": 4}]}, {"frames": [{"s": 249, "d": 2}, {"s": 250, "d": 1}, {"s": 251, "d": 9}, {"s": 249, "d": 10}]}, {"frames": [{"s": 256, "d": 3}, {"s": 257, "d": 1}, {"s": 258, "d": 4}, {"s": 259, "d": 2}, {"s": 260, "d": 12}]}, {"frames": [{"s": 261, "d": 4}, {"s": 262, "d": 2}, {"s": 263, "d": 2}, {"s": 264, "d": 2}, {"s": 264, "d": 4}, {"s": 265, "d": 4}, {"s": 266, "d": 4}, {"s": 267, "d": 4}, {"s": 81, "d": 4}]}, {"frames": [{"s": 210, "d": 2}, {"s": 268, "d": 1}, {"s": 269, "d": 12}, {"s": 269, "d": 2}, {"s": 210, "d": 6}]}, {"frames": [{"s": 270, "d": 3}, {"s": 271, "d": 1}, {"s": 272, "d": 2}, {"s": 273, "d": 12}, {"s": 273, "d": 12}, {"s": 274, "d": 8}]}, {"frames": [{"s": 270, "d": 6}, {"s": 275, "d": 4}, {"s": 276, "d": 4}, {"s": 277, "d": 4}, {"s": 278, "d": 4}, {"s": 275, "d": 4}, {"s": 276, "d": 4}, {"s": 277, "d": 4}, {"s": 278, "d": 6}, {"s": 210, "d": 8}]}, {"frames": [{"s": 210, "d": 2}, {"s": 268, "d": 1}, {"s": 269, "d": 12}, {"s": 269, "d": 2}, {"s": 210, "d": 6}]}, {"frames": [{"s": 270, "d": 3}, {"s": 271, "d": 1}, {"s": 272, "d": 2}, {"s": 273, "d": 12}, {"s": 273, "d": 12}, {"s": 274, "d": 8}]}, {"frames": [{"s": 249, "d": 7}, {"s": 382, "d": 2}, {"s": 383, "d": 2}]}, {"frames": [{"s": 391, "d": 5}, {"s": 392, "d": 3}, {"s": 393, "d": 3}]}, {"frames": [{"s": 394, "d": 8}, {"s": 392, "d": 2}, {"s": 94, "d": 2}, {"s": 95, "d": 2}, {"s": 38, "d": 2}, {"s": 96, "d": 1}, {"s": 97, "d": 1}]}, {"frames": [{"s": 395, "d": 8}, {"s": 396, "d": 4}, {"s": 397, "d": 4}, {"s": 398, "d": 2}, {"s": 399, "d": 2}, {"s": 96, "d": 2}, {"s": 97, "d": 2}]}, {"frames": [{"s": 400, "d": 5}, {"s": 401, "d": 3}, {"s": 97, "d": 3}]}, {"frames": [{"s": 402, "d": 8}, {"s": 403, "d": 2}, {"s": 404, "d": 2}, {"s": 408, "d": 2}, {"s": 95, "d": 2}, {"s": 38, "d": 1}, {"s": 96, "d": 1}]}, {"frames": [{"s": 405, "d": 8}, {"s": 406, "d": 4}, {"s": 407, "d": 4}, {"s": 95, "d": 2}, {"s": 38, "d": 2}, {"s": 408, "d": 2}, {"s": 97, "d": 2}]}, {"frames": [{"s": 409, "d": 6}, {"s": 95, "d": 5}]}, {"frames": [{"s": 410, "d": 10}, {"s": 411, "d": 4}, {"s": 412, "d": 2}, {"s": 95, "d": 2}]}, {"frames": [{"s": 413, "d": 10}, {"s": 414, "d": 4}, {"s": 415, "d": 4}, {"s": 412, "d": 3}, {"s": 95, "d": 3}]}, {"frames": [{"s": 400, "d": 5}, {"s": 420, "d": 5}, {"s": 421, "d": 5}, {"s": 429, "d": 3}, {"s": 422, "d": 2}, {"s": 433, "d": 2}, {"s": 462, "d": 6}]}, {"frames": [{"s": 416, "d": 10}]}, {"frames": [{"s": 417, "d": 10}]}, {"frames": [{"s": 418, "d": 10}]}, {"frames": [{"s": 433, "d": 2}, {"s": 434, "d": 2}, {"s": 433, "d": 2}, {"s": 462, "d": 2}]}, {"frames": [{"s": 433, "d": 2}, {"s": 434, "d": 2}, {"s": 433, "d": 2}, {"s": 462, "d": 2}]}, {"frames": [{"s": 433, "d": 2}, {"s": 434, "d": 2}, {"s": 433, "d": 2}, {"s": 462, "d": 2}]}, {"frames": [{"s": 423, "d": 2}, {"s": 424, "d": 2}]}, {"frames": [{"s": 426, "d": 4}]}, {"frames": [{"s": 428, "d": 4}]}, {"frames": [{"s": 430, "d": 4}]}, {"frames": [{"s": 432, "d": 4}]}, {"frames": [{"s": 423, "d": 2}, {"s": 424, "d": 2}, {"s": 426, "d": 4}, {"s": 428, "d": 4}, {"s": 430, "d": 4}, {"s": 431, "d": 2}, {"s": 432, "d": 4}]}, {"frames": [{"s": 426, "d": 4}, {"s": 428, "d": 4}, {"s": 430, "d": 4}, {"s": 431, "d": 2}, {"s": 432, "d": 4}]}, {"frames": [{"s": 428, "d": 4}, {"s": 430, "d": 4}, {"s": 431, "d": 2}, {"s": 432, "d": 4}]}, {"frames": [{"s": 430, "d": 4}, {"s": 431, "d": 2}, {"s": 432, "d": 4}]}, {"frames": [{"s": 432, "d": 4}]}, {"frames": [{"s": 433, "d": 3}, {"s": 434, "d": 3}, {"s": 433, "d": 3}, {"s": 462, "d": 3}]}, {"frames": [{"s": 435, "d": 2}, {"s": 436, "d": 2}, {"s": 437, "d": 2}, {"s": 438, "d": 2}, {"s": 439, "d": 2}, {"s": 440, "d": 2}, {"s": 441, "d": 2}, {"s": 442, "d": 2}, {"s": 82, "d": 4}, {"s": 89, "d": 4}]}, {"frames": [{"s": 443, "d": 4}, {"s": 444, "d": 4}, {"s": 445, "d": 4}, {"s": 446, "d": 4}, {"s": 447, "d": 4}, {"s": 448, "d": 4}]}, {"frames": [{"s": 449, "d": 4}, {"s": 450, "d": 4}, {"s": 451, "d": 4}, {"s": 452, "d": 4}, {"s": 453, "d": 4}, {"s": 454, "d": 4}]}, {"frames": [{"s": 435, "d": 2}, {"s": 436, "d": 2}, {"s": 437, "d": 2}, {"s": 438, "d": 2}, {"s": 439, "d": 2}, {"s": 440, "d": 2}, {"s": 441, "d": 2}, {"s": 442, "d": 2}, {"s": 82, "d": 4}, {"s": 89, "d": 4}]}, {"frames": [{"s": 462, "d": 4}]}, {"frames": [{"s": 435, "d": 2}, {"s": 436, "d": 2}, {"s": 437, "d": 2}, {"s": 438, "d": 2}, {"s": 439, "d": 2}, {"s": 440, "d": 2}, {"s": 441, "d": 2}, {"s": 442, "d": 2}, {"s": 82, "d": 4}, {"s": 89, "d": 4}]}, {"frames": [{"s": 159, "d": 3}, {"s": 158, "d": 3}, {"s": 148, "d": 3}, {"s": 212, "d": 3}, {"s": 211, "d": 3}]}, {"frames": [{"s": 433, "d": 2}, {"s": 434, "d": 2}, {"s": 433, "d": 2}, {"s": 462, "d": 2}]}, {"frames": [{"s": 455, "d": 4}, {"s": 456, "d": 4}, {"s": 457, "d": 4}, {"s": 458, "d": 4}, {"s": 459, "d": 4}, {"s": 460, "d": 4}, {"s": 461, "d": 4}]}, {"frames": [{"s": 21, "d": 4}, {"s": 22, "d": 4}, {"s": 23, "d": 4}, {"s": 24, "d": 4}, {"s": 25, "d": 4}, {"s": 26, "d": 4}, {"s": 27, "d": 4}, {"s": 28, "d": 4}, {"s": 29, "d": 4}, {"s": 30, "d": 4}, {"s": 31, "d": 4}, {"s": 32, "d": 4}, {"s": 33, "d": 4}, {"s": 34, "d": 4}, {"s": 35, "d": 4}, {"s": 36, "d": 4}, {"s": 37, "d": 4}]}, {"frames": [{"s": 281, "d": 12}, {"s": 282, "d": 24}, {"s": 291, "d": 9}, {"s": 283, "d": 12}, {"s": 283, "d": 8}, {"s": 290, "d": 12}, {"s": 291, "d": 8}]}, {"frames": [{"s": 284, "d": 10}, {"s": 285, "d": 3}, {"s": 286, "d": 3}, {"s": 287, "d": 3}, {"s": 288, "d": 1}, {"s": 288, "d": 9}, {"s": 289, "d": 10}]}, {"frames": [{"s": 292, "d": 8}, {"s": 293, "d": 8}, {"s": 294, "d": 8}, {"s": 295, "d": 48}, {"s": 296, "d": 12}, {"s": 297, "d": 8}, {"s": 296, "d": 4}, {"s": 298, "d": 8}, {"s": 296, "d": 4}]}, {"frames": [{"s": 77, "d": 2}, {"s": 78, "d": 2}, {"s": 85, "d": 2}, {"s": 84, "d": 2}, {"s": 83, "d": 2}, {"s": 82, "d": 2}, {"s": 81, "d": 2}, {"s": 80, "d": 48}]}, {"frames": [{"s": 364, "d": 12}, {"s": 364, "d": 6}, {"s": 298, "d": 8}, {"s": 363, "d": 8}, {"s": 364, "d": 10}]}, {"frames": [{"s": 295, "d": 8}, {"s": 362, "d": 22}]}, {"frames": [{"s": 391, "d": 1}]}, {"frames": [{"s": 394, "d": 1}]}, {"frames": [{"s": 395, "d": 1}]}, {"frames": [{"s": 400, "d": 1}]}, {"frames": [{"s": 402, "d": 1}]}, {"frames": [{"s": 405, "d": 1}]}, {"frames": [{"s": 409, "d": 1}]}, {"frames": [{"s": 410, "d": 1}]}, {"frames": [{"s": 413, "d": 1}]}, {"frames": [{"s": 391, "d": 1}]}, {"frames": [{"s": 394, "d": 1}]}, {"frames": [{"s": 395, "d": 1}]}, {"frames": [{"s": 419, "d": 4}]}, {"frames": [{"s": 423, "d": 1}]}, {"frames": [{"s": 426, "d": 1}]}, {"frames": [{"s": 428, "d": 1}]}, {"frames": [{"s": 430, "d": 1}]}, {"frames": [{"s": 432, "d": 1}]}, {"frames": [{"s": 443, "d": 1}]}, {"frames": [{"s": 449, "d": 1}]}, {"frames": [{"s": 462, "d": 1}]}, {"frames": [{"s": 462, "d": 1}]}, {"frames": [{"s": 144, "d": 3}, {"s": 145, "d": 3}, {"s": 146, "d": 3}, {"s": 147, "d": 3}, {"s": 148, "d": 3}, {"s": 149, "d": 3}, {"s": 150, "d": 3}, {"s": 151, "d": 3}, {"s": 95, "d": 3}, {"s": 96, "d": 3}]}, {"frames": [{"s": 144, "d": 1}, {"s": 153, "d": 1}, {"s": 154, "d": 1}, {"s": 155, "d": 1}, {"s": 156, "d": 1}, {"s": 157, "d": 1}, {"s": 158, "d": 1}, {"s": 159, "d": 1}, {"s": 160, "d": 2}, {"s": 148, "d": 2}, {"s": 149, "d": 2}, {"s": 150, "d": 2}, {"s": 151, "d": 2}]}, {"frames": [{"s": 144, "d": 2}, {"s": 153, "d": 2}, {"s": 154, "d": 2}, {"s": 155, "d": 2}, {"s": 156, "d": 2}, {"s": 157, "d": 4}, {"s": 158, "d": 4}, {"s": 159, "d": 4}, {"s": 160, "d": 4}, {"s": 148, "d": 4}, {"s": 149, "d": 4}, {"s": 150, "d": 4}, {"s": 151, "d": 4}]}, {"frames": [{"s": 144, "d": 2}, {"s": 153, "d": 2}, {"s": 160, "d": 2}, {"s": 159, "d": 2}, {"s": 158, "d": 2}, {"s": 157, "d": 2}, {"s": 156, "d": 2}, {"s": 155, "d": 2}, {"s": 154, "d": 2}, {"s": 148, "d": 2}, {"s": 149, "d": 2}, {"s": 150, "d": 4}, {"s": 151, "d": 4}]}, {"frames": [{"s": 125, "d": 1}, {"s": 126, "d": 2}, {"s": 127, "d": 1}, {"s": 128, "d": 2}, {"s": 129, "d": 1}, {"s": 130, "d": 2}, {"s": 131, "d": 1}, {"s": 132, "d": 2}]}, {"frames": [{"s": 85, "d": 3}, {"s": 84, "d": 3}, {"s": 83, "d": 3}, {"s": 82, "d": 3}, {"s": 81, "d": 3}, {"s": 80, "d": 2}, {"s": 85, "d": 2}]}, {"frames": [{"s": 133, "d": 1}, {"s": 133, "d": 3}, {"s": 134, "d": 4}, {"s": 135, "d": 8}, {"s": 136, "d": 4}, {"s": 137, "d": 5}, {"s": 138, "d": 6}, {"s": 139, "d": 6}, {"s": 140, "d": 3}, {"s": 141, "d": 3}, {"s": 142, "d": 4}, {"s": 143, "d": 4}, {"s": 399, "d": 5}, {"s": 97, "d": 4}]}, {"frames": [{"s": 113, "d": 5}, {"s": 113, "d": 1}, {"s": 114, "d": 7}, {"s": 115, "d": 8}, {"s": 116, "d": 20}, {"s": 117, "d": 8}, {"s": 118, "d": 6}, {"s": 119, "d": 8}, {"s": 120, "d": 12}, {"s": 120, "d": 1}, {"s": 120, "d": 4}]}, {"frames": [{"s": 310, "d": 7}, {"s": 302, "d": 7}, {"s": 303, "d": 7}, {"s": 304, "d": 7}, {"s": 305, "d": 7}, {"s": 306, "d": 7}, {"s": 307, "d": 7}, {"s": 308, "d": 7}, {"s": 309, "d": 7}, {"s": 310, "d": 7}, {"s": 311, "d": 7}]}, {"frames": [{"s": 124, "d": 6}, {"s": 121, "d": 20}, {"s": 122, "d": 6}, {"s": 123, "d": 4}]}, {"frames": [{"s": 310, "d": 7}, {"s": 302, "d": 7}, {"s": 303, "d": 7}, {"s": 304, "d": 7}, {"s": 305, "d": 7}, {"s": 306, "d": 7}, {"s": 307, "d": 7}, {"s": 308, "d": 7}, {"s": 309, "d": 7}, {"s": 310, "d": 7}, {"s": 311, "d": 7}]}, {"frames": [{"s": 243, "d": 5}, {"s": 244, "d": 1}, {"s": 245, "d": 2}, {"s": 245, "d": 2}, {"s": 245, "d": 8}, {"s": 246, "d": 4}, {"s": 247, "d": 4}, {"s": 248, "d": 6}, {"s": 94, "d": 5}, {"s": 95, "d": 4}]}, {"frames": [{"s": 103, "d": 6}, {"s": 312, "d": 4}, {"s": 314, "d": 3}, {"s": 315, "d": 4}]}, {"frames": [{"s": 316, "d": 2}, {"s": 317, "d": 2}, {"s": 318, "d": 2}, {"s": 319, "d": 2}]}, {"frames": [{"s": 320, "d": 2}, {"s": 313, "d": 2}, {"s": 314, "d": 2}, {"s": 315, "d": 2}]}, {"frames": [{"s": 361, "d": 255}]}, {"frames": [{"s": 361, "d": 3}, {"s": 356, "d": 3}, {"s": 357, "d": 3}, {"s": 358, "d": 3}, {"s": 359, "d": 3}, {"s": 360, "d": 3}]}, {"frames": [{"s": 94, "d": 1}, {"s": 95, "d": 2}, {"s": 38, "d": 2}, {"s": 96, "d": 1}, {"s": 97, "d": 1}]}, {"frames": [{"s": 94, "d": 3}, {"s": 95, "d": 4}, {"s": 38, "d": 3}, {"s": 96, "d": 3}, {"s": 97, "d": 2}]}, {"frames": [{"s": 94, "d": 3}, {"s": 95, "d": 4}, {"s": 38, "d": 3}, {"s": 96, "d": 3}, {"s": 97, "d": 2}]}, {"frames": [{"s": 94, "d": 4}, {"s": 95, "d": 8}]}, {"frames": [{"s": 435, "d": 1}, {"s": 442, "d": 1}, {"s": 441, "d": 1}, {"s": 440, "d": 1}, {"s": 439, "d": 1}, {"s": 438, "d": 1}, {"s": 437, "d": 1}, {"s": 436, "d": 1}]}, {"frames": [{"s": 322, "d": 1}, {"s": 323, "d": 1}, {"s": 324, "d": 1}, {"s": 325, "d": 1}, {"s": 326, "d": 1}, {"s": 321, "d": 1}, {"s": 322, "d": 1}, {"s": 323, "d": 1}, {"s": 324, "d": 1}, {"s": 325, "d": 1}, {"s": 326, "d": 1}, {"s": 321, "d": 1}, {"s": 322, "d": 2}, {"s": 323, "d": 2}, {"s": 324, "d": 2}, {"s": 325, "d": 2}, {"s": 326, "d": 2}, {"s": 321, "d": 2}]}, {"frames": [{"s": 355, "d": 3}, {"s": 442, "d": 1}, {"s": 441, "d": 2}, {"s": 440, "d": 1}, {"s": 439, "d": 2}, {"s": 438, "d": 1}, {"s": 437, "d": 2}, {"s": 436, "d": 1}, {"s": 435, "d": 2}]}, {"frames": [{"s": 328, "d": 1}, {"s": 329, "d": 1}, {"s": 330, "d": 1}, {"s": 331, "d": 1}, {"s": 332, "d": 1}, {"s": 327, "d": 1}, {"s": 328, "d": 1}, {"s": 329, "d": 1}, {"s": 330, "d": 1}, {"s": 331, "d": 1}, {"s": 332, "d": 1}, {"s": 327, "d": 1}, {"s": 328, "d": 2}, {"s": 329, "d": 2}, {"s": 330, "d": 2}, {"s": 331, "d": 2}, {"s": 332, "d": 2}, {"s": 327, "d": 2}]}, {"frames": [{"s": 351, "d": 3}, {"s": 442, "d": 1}, {"s": 441, "d": 2}, {"s": 440, "d": 1}, {"s": 439, "d": 2}, {"s": 438, "d": 1}, {"s": 437, "d": 2}, {"s": 436, "d": 1}, {"s": 435, "d": 2}]}, {"frames": [{"s": 334, "d": 1}, {"s": 335, "d": 1}, {"s": 336, "d": 1}, {"s": 337, "d": 1}, {"s": 338, "d": 1}, {"s": 333, "d": 1}, {"s": 334, "d": 1}, {"s": 335, "d": 1}, {"s": 336, "d": 1}, {"s": 337, "d": 1}, {"s": 338, "d": 1}, {"s": 333, "d": 1}, {"s": 334, "d": 2}, {"s": 335, "d": 2}, {"s": 336, "d": 2}, {"s": 337, "d": 2}, {"s": 338, "d": 2}, {"s": 333, "d": 2}]}, {"frames": [{"s": 352, "d": 3}, {"s": 442, "d": 1}, {"s": 441, "d": 2}, {"s": 440, "d": 1}, {"s": 439, "d": 2}, {"s": 438, "d": 1}, {"s": 437, "d": 2}, {"s": 436, "d": 1}, {"s": 435, "d": 2}]}, {"frames": [{"s": 340, "d": 1}, {"s": 341, "d": 1}, {"s": 342, "d": 1}, {"s": 343, "d": 1}, {"s": 344, "d": 1}, {"s": 339, "d": 1}, {"s": 340, "d": 1}, {"s": 341, "d": 1}, {"s": 342, "d": 1}, {"s": 343, "d": 1}, {"s": 344, "d": 1}, {"s": 339, "d": 1}, {"s": 340, "d": 2}, {"s": 341, "d": 2}, {"s": 342, "d": 2}, {"s": 343, "d": 2}, {"s": 344, "d": 2}, {"s": 339, "d": 2}]}, {"frames": [{"s": 353, "d": 3}, {"s": 442, "d": 1}, {"s": 441, "d": 2}, {"s": 440, "d": 1}, {"s": 439, "d": 2}, {"s": 438, "d": 1}, {"s": 437, "d": 2}, {"s": 436, "d": 1}, {"s": 435, "d": 2}]}, {"frames": [{"s": 346, "d": 1}, {"s": 347, "d": 1}, {"s": 348, "d": 1}, {"s": 349, "d": 1}, {"s": 350, "d": 1}, {"s": 345, "d": 1}, {"s": 346, "d": 1}, {"s": 347, "d": 1}, {"s": 348, "d": 1}, {"s": 349, "d": 1}, {"s": 350, "d": 1}, {"s": 345, "d": 1}, {"s": 346, "d": 2}, {"s": 347, "d": 2}, {"s": 348, "d": 2}, {"s": 349, "d": 2}, {"s": 350, "d": 2}, {"s": 345, "d": 2}]}, {"frames": [{"s": 354, "d": 3}, {"s": 442, "d": 2}, {"s": 441, "d": 2}, {"s": 440, "d": 2}, {"s": 439, "d": 2}, {"s": 438, "d": 2}, {"s": 437, "d": 2}, {"s": 436, "d": 2}, {"s": 435, "d": 2}]}, {"frames": [{"s": 299, "d": 4}, {"s": 300, "d": 10}]}, {"frames": [{"s": 94, "d": 4}, {"s": 95, "d": 10}]}, {"frames": [{"s": 375, "d": 4}, {"s": 73, "d": 3}]}, {"frames": [{"s": 375, "d": 10}, {"s": 73, "d": 5}]}, {"frames": [{"s": 375, "d": 10}, {"s": 73, "d": 5}]}, {"frames": [{"s": 368, "d": 2}, {"s": 369, "d": 2}, {"s": 370, "d": 2}]}, {"frames": [{"s": 368, "d": 3}, {"s": 369, "d": 3}, {"s": 370, "d": 3}]}, {"frames": [{"s": 375, "d": 10}, {"s": 73, "d": 5}]}, {"frames": [{"s": 365, "d": 2}, {"s": 366, "d": 2}, {"s": 367, "d": 2}]}, {"frames": [{"s": 365, "d": 3}, {"s": 366, "d": 3}, {"s": 367, "d": 3}]}, {"frames": [{"s": 375, "d": 10}, {"s": 73, "d": 5}]}, {"frames": [{"s": 397, "d": 3}, {"s": 398, "d": 8}, {"s": 399, "d": 4}, {"s": 96, "d": 4}, {"s": 97, "d": 4}]}, {"frames": [{"s": 397, "d": 5}, {"s": 398, "d": 9}, {"s": 399, "d": 7}, {"s": 96, "d": 5}, {"s": 97, "d": 6}]}, {"frames": [{"s": 375, "d": 10}, {"s": 73, "d": 5}]}, {"frames": [{"s": 210, "d": 4}, {"s": 268, "d": 2}, {"s": 269, "d": 2}]}, {"frames": [{"s": 175, "d": 2}, {"s": 176, "d": 2}, {"s": 175, "d": 2}, {"s": 176, "d": 2}, {"s": 177, "d": 2}, {"s": 178, "d": 2}, {"s": 177, "d": 2}, {"s": 178, "d": 2}, {"s": 179, "d": 2}, {"s": 180, "d": 2}, {"s": 179, "d": 2}, {"s": 180, "d": 2}, {"s": 100, "d": 6}, {"s": 101, "d": 5}, {"s": 102, "d": 5}]}, {"frames": [{"s": 38, "d": 3}, {"s": 197, "d": 5}]}, {"frames": [{"s": 38, "d": 3}, {"s": 197, "d": 11}]}, {"frames": [{"s": 38, "d": 3}, {"s": 197, "d": 11}]}, {"frames": [{"s": 72, "d": 2}, {"s": 73, "d": 1}, {"s": 74, "d": 1}, {"s": 75, "d": 1}]}, {"frames": [{"s": 197, "d": 5}, {"s": 197, "d": 1}, {"s": 198, "d": 1}, {"s": 199, "d": 1}, {"s": 200, "d": 12}, {"s": 201, "d": 8}]}, {"frames": [{"s": 95, "d": 4}, {"s": 38, "d": 4}, {"s": 96, "d": 4}, {"s": 97, "d": 4}]}, {"frames": [{"s": 95, "d": 4}, {"s": 38, "d": 4}, {"s": 96, "d": 4}, {"s": 97, "d": 4}]}, {"frames": [{"s": 95, "d": 4}, {"s": 38, "d": 4}, {"s": 96, "d": 4}, {"s": 97, "d": 4}]}, {"frames": [{"s": 197, "d": 8}, {"s": 197, "d": 2}, {"s": 198, "d": 2}, {"s": 199, "d": 2}, {"s": 200, "d": 14}, {"s": 201, "d": 8}, {"s": 95, "d": 2}, {"s": 38, "d": 4}, {"s": 96, "d": 4}, {"s": 97, "d": 2}]}, {"frames": [{"s": 133, "d": 4}, {"s": 134, "d": 3}, {"s": 135, "d": 4}, {"s": 136, "d": 2}, {"s": 137, "d": 3}, {"s": 138, "d": 4}, {"s": 139, "d": 4}, {"s": 140, "d": 2}, {"s": 141, "d": 2}, {"s": 142, "d": 2}, {"s": 143, "d": 2}, {"s": 143, "d": 6}, {"s": 143, "d": 2}, {"s": 71, "d": 2}, {"s": 71, "d": 2}, {"s": 72, "d": 1}, {"s": 73, "d": 3}, {"s": 74, "d": 1}, {"s": 75, "d": 1}, {"s": 76, "d": 2}]}, {"frames": [{"s": 182, "d": 2}, {"s": 181, "d": 2}, {"s": 182, "d": 2}, {"s": 183, "d": 2}, {"s": 184, "d": 2}, {"s": 185, "d": 2}, {"s": 186, "d": 2}, {"s": 187, "d": 2}, {"s": 188, "d": 2}, {"s": 189, "d": 2}, {"s": 190, "d": 2}, {"s": 191, "d": 2}, {"s": 192, "d": 2}, {"s": 193, "d": 2}, {"s": 194, "d": 2}, {"s": 195, "d": 2}, {"s": 202, "d": 2}, {"s": 203, "d": 2}, {"s": 204, "d": 2}, {"s": 204, "d": 2}, {"s": 205, "d": 2}, {"s": 249, "d": 2}, {"s": 250, "d": 2}, {"s": 251, "d": 2}, {"s": 251, "d": 2}, {"s": 269, "d": 2}, {"s": 269, "d": 2}, {"s": 252, "d": 2}, {"s": 253, "d": 2}, {"s": 254, "d": 2}, {"s": 255, "d": 2}, {"s": 256, "d": 2}, {"s": 257, "d": 2}, {"s": 258, "d": 2}, {"s": 259, "d": 2}, {"s": 260, "d": 2}, {"s": 271, "d": 2}, {"s": 272, "d": 2}, {"s": 273, "d": 2}, {"s": 273, "d": 2}, {"s": 274, "d": 2}, {"s": 261, "d": 2}, {"s": 262, "d": 2}, {"s": 263, "d": 2}, {"s": 264, "d": 2}, {"s": 265, "d": 2}, {"s": 266, "d": 2}, {"s": 267, "d": 2}, {"s": 94, "d": 2}, {"s": 95, "d": 2}]}, {"frames": [{"s": 371, "d": 2}, {"s": 372, "d": 2}, {"s": 371, "d": 2}, {"s": 372, "d": 2}]}, {"frames": [{"s": 94, "d": 5}, {"s": 95, "d": 5}, {"s": 38, "d": 5}, {"s": 96, "d": 5}, {"s": 97, "d": 5}]}, {"frames": [{"s": 397, "d": 4}, {"s": 398, "d": 9}, {"s": 399, "d": 5}, {"s": 96, "d": 4}, {"s": 97, "d": 4}]}, {"frames": [{"s": 375, "d": 16}, {"s": 375, "d": 1}]}, {"frames": [{"s": 375, "d": 6}, {"s": 375, "d": 4}, {"s": 375, "d": 1}, {"s": 375, "d": 1}]}, {"frames": [{"s": 368, "d": 1}, {"s": 369, "d": 1}, {"s": 370, "d": 1}]}, {"frames": [{"s": 365, "d": 1}, {"s": 366, "d": 1}, {"s": 367, "d": 1}]}, {"frames": [{"s": 397, "d": 6}, {"s": 398, "d": 10}, {"s": 399, "d": 8}, {"s": 96, "d": 6}, {"s": 97, "d": 6}]}, {"frames": [{"s": 197, "d": 6}, {"s": 198, "d": 4}, {"s": 199, "d": 4}, {"s": 200, "d": 24}, {"s": 201, "d": 8}, {"s": 95, "d": 4}, {"s": 38, "d": 4}, {"s": 96, "d": 4}, {"s": 97, "d": 4}]}, {"frames": [{"s": 197, "d": 10}, {"s": 197, "d": 10}, {"s": 372, "d": 2}, {"s": 371, "d": 2}, {"s": 372, "d": 2}]}, {"frames": [{"s": 435, "d": 2}, {"s": 442, "d": 2}, {"s": 441, "d": 2}, {"s": 440, "d": 2}, {"s": 439, "d": 2}, {"s": 438, "d": 2}, {"s": 437, "d": 2}, {"s": 435, "d": 2}, {"s": 442, "d": 2}, {"s": 441, "d": 2}, {"s": 440, "d": 2}, {"s": 439, "d": 2}, {"s": 438, "d": 2}, {"s": 437, "d": 2}, {"s": 442, "d": 2}, {"s": 442, "d": 1}]}, {"frames": [{"s": 384, "d": 3}, {"s": 385, "d": 3}]}, {"frames": [{"s": 167, "d": 4}, {"s": 168, "d": 8}, {"s": 169, "d": 1}, {"s": 170, "d": 1}, {"s": 171, "d": 1}, {"s": 172, "d": 1}, {"s": 173, "d": 3}, {"s": 174, "d": 16}, {"s": 196, "d": 4}]}, {"frames": [{"s": 548, "d": 10}, {"s": 549, "d": 5}, {"s": 550, "d": 5}, {"s": 551, "d": 5}, {"s": 552, "d": 5}, {"s": 553, "d": 5}, {"s": 554, "d": 5}]}, {"frames": [{"s": 555, "d": 10}, {"s": 556, "d": 5}, {"s": 557, "d": 5}, {"s": 558, "d": 5}, {"s": 559, "d": 5}, {"s": 560, "d": 5}]}, {"frames": [{"s": 488, "d": 1}, {"s": 489, "d": 1}, {"s": 490, "d": 1}, {"s": 491, "d": 1}, {"s": 4, "d": 1}, {"s": 5, "d": 1}, {"s": 498, "d": 1}, {"s": 499, "d": 1}]}, {"frames": [{"s": 0, "d": 1}, {"s": 1, "d": 1}, {"s": 2, "d": 1}, {"s": 3, "d": 1}]}, {"frames": [{"s": 6, "d": 1}, {"s": 7, "d": 1}, {"s": 8, "d": 1}, {"s": 9, "d": 1}]}, {"frames": [{"s": 500, "d": 1}, {"s": 501, "d": 1}, {"s": 502, "d": 1}, {"s": 503, "d": 1}, {"s": 10, "d": 1}, {"s": 11, "d": 1}, {"s": 510, "d": 1}, {"s": 511, "d": 1}]}, {"frames": [{"s": 488, "d": 2}, {"s": 489, "d": 2}, {"s": 490, "d": 2}, {"s": 491, "d": 2}, {"s": 4, "d": 2}, {"s": 5, "d": 2}, {"s": 498, "d": 2}, {"s": 499, "d": 2}]}, {"frames": [{"s": 0, "d": 2}, {"s": 1, "d": 2}, {"s": 2, "d": 2}, {"s": 3, "d": 2}]}, {"frames": [{"s": 6, "d": 2}, {"s": 7, "d": 2}, {"s": 8, "d": 2}, {"s": 9, "d": 2}]}, {"frames": [{"s": 500, "d": 2}, {"s": 501, "d": 2}, {"s": 502, "d": 2}, {"s": 503, "d": 2}, {"s": 10, "d": 2}, {"s": 11, "d": 2}, {"s": 510, "d": 2}, {"s": 511, "d": 2}]}, {"frames": [{"s": 488, "d": 2}, {"s": 489, "d": 2}, {"s": 490, "d": 2}, {"s": 491, "d": 2}, {"s": 4, "d": 2}, {"s": 5, "d": 2}, {"s": 498, "d": 2}, {"s": 499, "d": 2}]}, {"frames": [{"s": 488, "d": 2}, {"s": 489, "d": 2}, {"s": 490, "d": 2}, {"s": 491, "d": 2}, {"s": 4, "d": 2}, {"s": 5, "d": 2}, {"s": 498, "d": 2}, {"s": 499, "d": 2}]}, {"frames": [{"s": 488, "d": 2}, {"s": 489, "d": 2}, {"s": 490, "d": 2}, {"s": 491, "d": 2}, {"s": 4, "d": 2}, {"s": 5, "d": 2}, {"s": 498, "d": 2}, {"s": 499, "d": 2}]}, {"frames": [{"s": 488, "d": 2}, {"s": 489, "d": 2}, {"s": 490, "d": 2}, {"s": 491, "d": 2}, {"s": 4, "d": 2}, {"s": 5, "d": 2}, {"s": 498, "d": 2}, {"s": 499, "d": 2}]}, {"frames": [{"s": 12, "d": 1}, {"s": 12, "d": 1}, {"s": 13, "d": 2}, {"s": 14, "d": 2}, {"s": 15, "d": 2}, {"s": 16, "d": 2}, {"s": 17, "d": 2}, {"s": 18, "d": 1}, {"s": 19, "d": 1}, {"s": 20, "d": 1}]}, {"frames": [{"s": 12, "d": 1}, {"s": 12, "d": 1}, {"s": 13, "d": 2}, {"s": 14, "d": 2}, {"s": 15, "d": 2}, {"s": 16, "d": 2}, {"s": 17, "d": 2}, {"s": 18, "d": 1}, {"s": 19, "d": 1}, {"s": 20, "d": 1}]}, {"frames": [{"s": 14, "d": 1}]}, {"frames": [{"s": 14, "d": 1}]}, {"frames": [{"s": 14, "d": 1}]}, {"frames": [{"s": 14, "d": 1}]}, {"frames": [{"s": 113, "d": 4}, {"s": 114, "d": 4}, {"s": 115, "d": 4}, {"s": 116, "d": 4}, {"s": 116, "d": 26}]}, {"frames": [{"s": 161, "d": 128}]}, {"frames": [{"s": 92, "d": 2}, {"s": 92, "d": 2}]}, {"frames": [{"s": 310, "d": 2}, {"s": 302, "d": 4}, {"s": 303, "d": 4}, {"s": 304, "d": 4}, {"s": 305, "d": 4}, {"s": 306, "d": 4}, {"s": 307, "d": 4}, {"s": 308, "d": 4}, {"s": 309, "d": 4}, {"s": 310, "d": 4}, {"s": 311, "d": 4}]}, {"frames": [{"s": 310, "d": 2}, {"s": 302, "d": 2}, {"s": 303, "d": 4}, {"s": 304, "d": 4}, {"s": 305, "d": 4}, {"s": 306, "d": 4}, {"s": 307, "d": 4}, {"s": 308, "d": 4}, {"s": 309, "d": 4}, {"s": 310, "d": 4}, {"s": 311, "d": 4}]}, {"frames": [{"s": 21, "d": 4}, {"s": 22, "d": 4}, {"s": 23, "d": 4}, {"s": 24, "d": 4}, {"s": 25, "d": 4}, {"s": 26, "d": 4}, {"s": 27, "d": 4}, {"s": 28, "d": 4}, {"s": 29, "d": 4}, {"s": 30, "d": 4}, {"s": 31, "d": 4}, {"s": 32, "d": 4}, {"s": 33, "d": 4}, {"s": 34, "d": 4}, {"s": 35, "d": 4}, {"s": 36, "d": 4}, {"s": 37, "d": 4}]}, {"frames": [{"s": 21, "d": 4}, {"s": 22, "d": 4}, {"s": 23, "d": 4}, {"s": 24, "d": 4}, {"s": 25, "d": 4}, {"s": 26, "d": 4}, {"s": 27, "d": 4}, {"s": 28, "d": 4}, {"s": 29, "d": 4}, {"s": 30, "d": 4}, {"s": 31, "d": 4}, {"s": 32, "d": 4}, {"s": 33, "d": 4}, {"s": 34, "d": 4}, {"s": 35, "d": 4}, {"s": 36, "d": 4}, {"s": 37, "d": 4}]}, {"frames": [{"s": 512, "d": 8}, {"s": 514, "d": 6}, {"s": 0, "d": 0}, {"s": 519, "d": 4}]}, {"frames": [{"s": 514, "d": 6}, {"s": 0, "d": 0}, {"s": 519, "d": 4}]}, {"frames": [{"s": 520, "d": 4}, {"s": 0, "d": 0}, {"s": 525, "d": 4}, {"s": 527, "d": 4}, {"s": 256, "d": 0}, {"s": 0, "d": 0}, {"s": 534, "d": 3}, {"s": 0, "d": 0}, {"s": 539, "d": 4}]}, {"frames": [{"s": 527, "d": 4}, {"s": 256, "d": 0}, {"s": 0, "d": 0}, {"s": 534, "d": 3}, {"s": 0, "d": 0}, {"s": 539, "d": 4}]}, {"frames": [{"s": 531, "d": 3}, {"s": 0, "d": 0}, {"s": 536, "d": 3}, {"s": 0, "d": 0}, {"s": 0, "d": 0}, {"s": 484, "d": 4}]}, {"frames": [{"s": 481, "d": 3}, {"s": 0, "d": 0}, {"s": 0, "d": 0}, {"s": 0, "d": 0}, {"s": 542, "d": 4}, {"s": 0, "d": 0}, {"s": 547, "d": 4}]}, {"frames": [{"s": 485, "d": 3}, {"s": 0, "d": 0}, {"s": 544, "d": 4}, {"s": 0, "d": 0}, {"s": 0, "d": 0}, {"s": 153, "d": 0}, {"s": 0, "d": 0}, {"s": 0, "d": 152}]}, {"frames": [{"s": 540, "d": 4}, {"s": 0, "d": 0}, {"s": 545, "d": 4}, {"s": 0, "d": 0}, {"s": 0, "d": 152}]}]